pyfbad/__init__.py
pyfbad/data/__init__.py
pyfbad/data/database.py
pyfbad/features/__init__.py
pyfbad/features/create_feature.py
pyfbad/models/__init__.py
pyfbad/models/models.py
pyfbad/notification/__init__.py
pyfbad/notification/notifications.py
pyfbad/visualization/__init__.py
pyfbad/visualization/visualizations.py
pyfbad-0.2.0.dist-info/LICENSE
pyfbad-0.2.0.dist-info/METADATA
pyfbad-0.2.0.dist-info/WHEEL
pyfbad-0.2.0.dist-info/top_level.txt
pyfbad-0.2.0.dist-info/RECORD
